[{
    "id": 1,
    "male": true,
    "female": false,
    "name": "Jimmy",
    "bald": false,
    "black hair": true,
    "white hair": false,
    "blonde hair": false,
    "red hair": false,
    "purple hair": false,
    "blue hair": false,
    "beard": false,
    "moustache": false,
    "glasses": false,
    "earrings": false,
    "hat": true,
    "brown skin": true,
    "pale skin": false,
    "image": "img/face1.jpg"
}, {
    "id": 2,
    "male": false,
    "female": true,
    "name": "Vanessa",
    "bald": false,
    "black hair": false,
    "white hair": false,
    "blonde hair": true,
    "red hair": false,
    "purple hair": false,
    "blue hair": false,
    "beard": false,
    "moustache": false,
    "glasses": false,
    "earrings": false,
    "hat": false,
    "brown skin": false,
    "pale skin": true,
    "image": "img/face2.jpg"
}, {
    "id": 3,
    "male": true,
    "female": false,
    "name": "Benjamin",
    "bald": true,
    "black hair": false,
    "white hair": true,
    "blonde hair": false,
    "red hair": false,
    "purple hair": false,
    "blue hair": false,
    "beard": false,
    "moustache": true,
    "glasses": false,
    "earrings": false,
    "hat": false,
    "brown skin": false,
    "pale skin": true,
    "image": "img/face3.jpg"
}, {
    "id": 4,
    "male": true,
    "female": false,
    "name": "Dylan",
    "bald": false,
    "black hair": false,
    "white hair": false,
    "blonde hair": false,
    "red hair": true,
    "purple hair": false,
    "blue hair": false,
    "beard": false,
    "moustache": false,
    "glasses": false,
    "earrings": false,
    "hat": false,
    "brown skin": false,
    "pale skin": true,
    "image": "img/face4.jpg"
}, {
    "id": 5,
    "male": false,
    "female": true,
    "name": "Sophie",
    "bald": true,
    "black hair": false,
    "white hair": false,
    "blonde hair": false,
    "red hair": false,
    "purple hair": true,
    "blue hair": false,
    "beard": false,
    "moustache": false,
    "glasses": true,
    "earrings": false,
    "hat": false,
    "brown skin": false,
    "pale skin": true,
    "image": "img/face5.jpg"
}, {
    "id": 6,
    "male": true,
    "female": false,
    "name": "Andrew",
    "bald": false,
    "black hair": false,
    "white hair": false,
    "blonde hair": false,
    "red hair": false,
    "purple hair": false,
    "blue hair": true,
    "beard": true,
    "moustache": false,
    "glasses": true,
    "earrings": false,
    "hat": false,
    "brown skin": true,
    "pale skin": false,
    "image": "img/face6.jpg"
}, {
    "id": 7,
    "male": false,
    "female": true,
    "name": "Laura",
    "bald": false,
    "black hair": false,
    "white hair": false,
    "blonde hair": false,
    "red hair": false,
    "purple hair": false,
    "blue hair": true,
    "beard": false,
    "moustache": false,
    "glasses": false,
    "earrings": false,
    "hat": true,
    "brown skin": false,
    "pale skin": true,
    "image": "img/face7.jpg"
}, {
    "id": 8,
    "male": false,
    "female": true,
    "name": "Maria",
    "bald": false,
    "black hair": false,
    "white hair": false,
    "blonde hair": false,
    "red hair": false,
    "purple hair": true,
    "blue hair": false,
    "beard": false,
    "moustache": false,
    "glasses": false,
    "earrings": true,
    "hat": true,
    "brown skin": false,
    "pale skin": true,
    "image": "img/face8.jpg"
}, {
    "id": 9,
    "male": false,
    "female": true,
    "name": "Julie",
    "bald": false,
    "black hair": false,
    "white hair": false,
    "blonde hair": false,
    "red hair": true,
    "purple hair": false,
    "blue hair": false,
    "beard": false,
    "moustache": false,
    "glasses": false,
    "earrings": true,
    "hat": false,
    "brown skin": false,
    "pale skin": true,
    "image": "img/face9.jpg"
}, {
    "id": 10,
    "male": true,
    "female": false,
    "name": "Ralph",
    "bald": false,
    "black hair": false,
    "white hair": false,
    "blonde hair": false,
    "red hair": false,
    "purple hair": true,
    "blue hair": false,
    "beard": false,
    "moustache": true,
    "glasses": true,
    "earrings": false,
    "hat": false,
    "brown skin": false,
    "pale skin": true,
    "image": "img/face10.jpg"
}, {
    "id": 11,
    "male": false,
    "female": true,
    "name": "Hayley",
    "bald": false,
    "black hair": false,
    "white hair": true,
    "blonde hair": false,
    "red hair": false,
    "purple hair": false,
    "blue hair": false,
    "beard": false,
    "moustache": false,
    "glasses": false,
    "earrings": true,
    "hat": false,
    "brown skin": true,
    "pale skin": false,
    "image": "img/face11.jpg"
}, {
    "id": 12,
    "male": false,
    "female": true,
    "name": "Suzie",
    "bald": false,
    "black hair": false,
    "white hair": false,
    "blonde hair": false,
    "red hair": true,
    "purple hair": false,
    "blue hair": false,
    "beard": false,
    "moustache": false,
    "glasses": false,
    "earrings": true,
    "hat": false,
    "brown skin": false,
    "pale skin": true,
    "image": "img/face12.jpg"
}, {
    "id": 13,
    "male": true,
    "female": false,
    "name": "Marvin",
    "bald": false,
    "black hair": true,
    "white hair": false,
    "blonde hair": false,
    "red hair": false,
    "purple hair": false,
    "blue hair": false,
    "beard": true,
    "moustache": false,
    "glasses": true,
    "earrings": false,
    "hat": false,
    "brown skin": false,
    "pale skin": true,
    "image": "img/face13.jpg"
}, {
    "id": 14,
    "male": true,
    "female": false,
    "name": "Eugene",
    "bald": true,
    "black hair": false,
    "white hair": false,
    "blonde hair": false,
    "red hair": false,
    "purple hair": false,
    "blue hair": false,
    "beard": true,
    "moustache": true,
    "glasses": false,
    "earrings": false,
    "hat": false,
    "brown skin": false,
    "pale skin": true,
    "image": "img/face14.jpg"
}, {
    "id": 15,
    "male": false,
    "female": true,
    "name": "Danielle",
    "bald": false,
    "black hair": false,
    "white hair": false,
    "blonde hair": true,
    "red hair": false,
    "purple hair": false,
    "blue hair": false,
    "beard": false,
    "moustache": false,
    "glasses": false,
    "earrings": true,
    "hat": false,
    "brown skin": false,
    "pale skin": true,
    "image": "img/face15.jpg"
}, {
    "id": 16,
    "male": true,
    "female": false,
    "name": "Bobby",
    "bald": false,
    "black hair": false,
    "white hair": false,
    "blonde hair": false,
    "red hair": false,
    "purple hair": false,
    "blue hair": true,
    "beard": false,
    "moustache": false,
    "glasses": false,
    "earrings": false,
    "hat": false,
    "brown skin": false,
    "pale skin": true,
    "image": "img/face16.jpg"
}, {
    "id": 17,
    "male": false,
    "female": true,
    "name": "Abagail",
    "bald": false,
    "black hair": false,
    "white hair": false,
    "blonde hair": false,
    "red hair": true,
    "purple hair": false,
    "blue hair": false,
    "beard": false,
    "moustache": false,
    "glasses": false,
    "earrings": false,
    "hat": false,
    "brown skin": false,
    "pale skin": true,
    "image": "img/face17.jpg"
}, {
    "id": 18,
    "male": true,
    "female": false,
    "name": "Harry",
    "bald": false,
    "black hair": false,
    "white hair": false,
    "blonde hair": false,
    "red hair": false,
    "purple hair": true,
    "blue hair": false,
    "beard": false,
    "moustache": false,
    "glasses": false,
    "earrings": true,
    "hat": false,
    "brown skin": false,
    "pale skin": true,
    "image": "img/face18.jpg"
}]
